yt_api_wrapper/__init__.py
yt_api_wrapper/async_yt_api_wrapper.py
yt_api_wrapper/models.py
yt_api_wrapper/parser.py
yt_api_wrapper/utils.py
yt_api_wrapper/yt_api_wrapper.py
yt_api_wrapper-1.0.4.dist-info/licenses/LICENSE
yt_api_wrapper-1.0.4.dist-info/METADATA
yt_api_wrapper-1.0.4.dist-info/WHEEL
yt_api_wrapper-1.0.4.dist-info/top_level.txt
yt_api_wrapper-1.0.4.dist-info/RECORD
