Metadata-Version: 2.4
Name: yt-api-wrapper
Version: 1.0.4
Summary: A YouTube web scraper/wrapper for fetching video metadata and search results.
Author-email: isa-programmer <isaprogrammer@proton.me>
License: MIT
Requires-Python: >=3.8
License-File: LICENSE
Requires-Dist: requests>=2.25.0
Provides-Extra: dev
Requires-Dist: pytest; extra == "dev"
Requires-Dist: mypy; extra == "dev"
Requires-Dist: black; extra == "dev"
Requires-Dist: isort; extra == "dev"
Provides-Extra: async
Requires-Dist: aiohttp[speedups]; extra == "async"
Provides-Extra: orjson
Requires-Dist: orjson>=3.6.8; extra == "orjson"
Dynamic: license-file
